odoo9_addon_contract_payment_mode-9.0.1.0.1-py2.7-nspkg.pth
odoo9_addon_contract_payment_mode-9.0.1.0.1.dist-info/DESCRIPTION.rst
odoo9_addon_contract_payment_mode-9.0.1.0.1.dist-info/METADATA
odoo9_addon_contract_payment_mode-9.0.1.0.1.dist-info/RECORD
odoo9_addon_contract_payment_mode-9.0.1.0.1.dist-info/WHEEL
odoo9_addon_contract_payment_mode-9.0.1.0.1.dist-info/metadata.json
odoo9_addon_contract_payment_mode-9.0.1.0.1.dist-info/namespace_packages.txt
odoo9_addon_contract_payment_mode-9.0.1.0.1.dist-info/top_level.txt
odoo_addons/contract_payment_mode/README.rst
odoo_addons/contract_payment_mode/__init__.py
odoo_addons/contract_payment_mode/__openerp__.py
odoo_addons/contract_payment_mode/hooks.py
odoo_addons/contract_payment_mode/i18n/ca.po
odoo_addons/contract_payment_mode/i18n/de.po
odoo_addons/contract_payment_mode/i18n/el_GR.po
odoo_addons/contract_payment_mode/i18n/es.po
odoo_addons/contract_payment_mode/i18n/es_MX.po
odoo_addons/contract_payment_mode/i18n/fi.po
odoo_addons/contract_payment_mode/i18n/fr.po
odoo_addons/contract_payment_mode/i18n/gl.po
odoo_addons/contract_payment_mode/i18n/hr.po
odoo_addons/contract_payment_mode/i18n/hr_HR.po
odoo_addons/contract_payment_mode/i18n/hu.po
odoo_addons/contract_payment_mode/i18n/it.po
odoo_addons/contract_payment_mode/i18n/nl.po
odoo_addons/contract_payment_mode/i18n/pt.po
odoo_addons/contract_payment_mode/i18n/pt_BR.po
odoo_addons/contract_payment_mode/i18n/pt_PT.po
odoo_addons/contract_payment_mode/i18n/ro.po
odoo_addons/contract_payment_mode/i18n/sk_SK.po
odoo_addons/contract_payment_mode/i18n/sl.po
odoo_addons/contract_payment_mode/i18n/zh_CN.po
odoo_addons/contract_payment_mode/models/__init__.py
odoo_addons/contract_payment_mode/models/contract.py
odoo_addons/contract_payment_mode/tests/__init__.py
odoo_addons/contract_payment_mode/tests/test_contract_payment.py
odoo_addons/contract_payment_mode/views/contract_view.xml
